dateutil/__init__.py
dateutil/_common.py
dateutil/_version.py
dateutil/easter.py
dateutil/relativedelta.py
dateutil/rrule.py
dateutil/tzwin.py
dateutil/utils.py
dateutil/parser/__init__.py
dateutil/parser/_parser.py
dateutil/parser/isoparser.py
dateutil/tz/__init__.py
dateutil/tz/_common.py
dateutil/tz/_factories.py
dateutil/tz/tz.py
dateutil/tz/win.py
dateutil/zoneinfo/__init__.py
dateutil/zoneinfo/rebuild.py
pyawscron/__init__.py
pyawscron/awscron.py
pyawscron/commons.py
pyawscron/occurrence.py
pyawscron/version.py
pyawscrondxcsesfrwk-1.0.0.dist-info/METADATA
pyawscrondxcsesfrwk-1.0.0.dist-info/WHEEL
pyawscrondxcsesfrwk-1.0.0.dist-info/top_level.txt
pyawscrondxcsesfrwk-1.0.0.dist-info/RECORD
