Metadata-Version: 2.1
Name: pyawscrondxcsesfrwk
Version: 1.0.0
Summary: A customized version of pyawscron limited to DXC
Home-page: https://github.com/pitchblack408/pyawscron.git
Author: AWS Platform Engineering
Author-email: abc@example.com
